IosDeHanshuXiangyingXingBiancheng/README.md
IosDeHanshuXiangyingXingBiancheng/__init__.py
IosDeHanshuXiangyingXingBiancheng/__main__.py
IosDeHanshuXiangyingXingBiancheng/file.epub
IosDeHanshuXiangyingXingBiancheng/index.html
IosDeHanshuXiangyingXingBiancheng/css/__init__.py
IosDeHanshuXiangyingXingBiancheng/css/annotations.css
IosDeHanshuXiangyingXingBiancheng/css/main.css
IosDeHanshuXiangyingXingBiancheng/css/normalize.css
IosDeHanshuXiangyingXingBiancheng/css/popup.css
IosDeHanshuXiangyingXingBiancheng/font/__init__.py
IosDeHanshuXiangyingXingBiancheng/font/fontello.eot
IosDeHanshuXiangyingXingBiancheng/font/fontello.svg
IosDeHanshuXiangyingXingBiancheng/font/fontello.ttf
IosDeHanshuXiangyingXingBiancheng/font/fontello.woff
IosDeHanshuXiangyingXingBiancheng/img/__init__.py
IosDeHanshuXiangyingXingBiancheng/img/annotator-glyph-sprite.png
IosDeHanshuXiangyingXingBiancheng/img/annotator-icon-sprite.png
IosDeHanshuXiangyingXingBiancheng/img/apple-touch-icon.png
IosDeHanshuXiangyingXingBiancheng/img/cancelfullscreen.png
IosDeHanshuXiangyingXingBiancheng/img/close.png
IosDeHanshuXiangyingXingBiancheng/img/fullscreen.png
IosDeHanshuXiangyingXingBiancheng/img/loader.gif
IosDeHanshuXiangyingXingBiancheng/img/menu-icon.png
IosDeHanshuXiangyingXingBiancheng/img/save.png
IosDeHanshuXiangyingXingBiancheng/img/saved.png
IosDeHanshuXiangyingXingBiancheng/img/settings-s.png
IosDeHanshuXiangyingXingBiancheng/img/settings.png
IosDeHanshuXiangyingXingBiancheng/img/star.png
IosDeHanshuXiangyingXingBiancheng/js/__init__.py
IosDeHanshuXiangyingXingBiancheng/js/epub.js
IosDeHanshuXiangyingXingBiancheng/js/epub.min.js
IosDeHanshuXiangyingXingBiancheng/js/epub.min.map
IosDeHanshuXiangyingXingBiancheng/js/hooks.min.js
IosDeHanshuXiangyingXingBiancheng/js/hooks.min.map
IosDeHanshuXiangyingXingBiancheng/js/reader.js
IosDeHanshuXiangyingXingBiancheng/js/reader.js.map
IosDeHanshuXiangyingXingBiancheng/js/reader.min.js
IosDeHanshuXiangyingXingBiancheng/js/reader.min.map
ios_de_hanshu_xiangying_xing_biancheng-2024.3.4.0.dist-info/METADATA
ios_de_hanshu_xiangying_xing_biancheng-2024.3.4.0.dist-info/WHEEL
ios_de_hanshu_xiangying_xing_biancheng-2024.3.4.0.dist-info/entry_points.txt
ios_de_hanshu_xiangying_xing_biancheng-2024.3.4.0.dist-info/top_level.txt
ios_de_hanshu_xiangying_xing_biancheng-2024.3.4.0.dist-info/RECORD
